[
  {
    "sent_id": 1,
    "text": "La intervención de Argúello ha derivado en encontronazo con el Gobierno.",
    "tokens": [
      {
        "id": 1,
        "text": "La",
        "lemma": "el",
        "upos": "DET",
        "xpos": "da0fs0",
        "feats": "Definite=Def|Gender=Fem|Number=Sing|PronType=Art",
        "head": 2,
        "deprel": "det",
        "start_char": 0,
        "end_char": 2
      },
      {
        "id": 2,
        "text": "intervención",
        "lemma": "intervención",
        "upos": "NOUN",
        "xpos": "ncfs000",
        "feats": "Gender=Fem|Number=Sing",
        "head": 6,
        "deprel": "nsubj",
        "start_char": 3,
        "end_char": 15
      },
      {
        "id": 3,
        "text": "de",
        "lemma": "de",
        "upos": "ADP",
        "xpos": "sps00",
        "feats": null,
        "head": 4,
        "deprel": "case",
        "start_char": 16,
        "end_char": 18
      },
      {
        "id": 4,
        "text": "Argúello",
        "lemma": "Argúello",
        "upos": "PROPN",
        "xpos": "np00000",
        "feats": null,
        "head": 2,
        "deprel": "nmod",
        "start_char": 19,
        "end_char": 27
      },
      {
        "id": 5,
        "text": "ha",
        "lemma": "haber",
        "upos": "AUX",
        "xpos": "vaip3s0",
        "feats": "Mood=Ind|Number=Sing|Person=3|Tense=Pres|VerbForm=Fin",
        "head": 6,
        "deprel": "aux",
        "start_char": 28,
        "end_char": 30
      },
      {
        "id": 6,
        "text": "derivado",
        "lemma": "derivar",
        "upos": "VERB",
        "xpos": "vmp00sm",
        "feats": "Gender=Masc|Number=Sing|Tense=Past|VerbForm=Part",
        "head": 0,
        "deprel": "root",
        "start_char": 31,
        "end_char": 39
      },
      {
        "id": 7,
        "text": "en",
        "lemma": "en",
        "upos": "ADP",
        "xpos": "sps00",
        "feats": null,
        "head": 8,
        "deprel": "case",
        "start_char": 40,
        "end_char": 42
      },
      {
        "id": 8,
        "text": "encontronazo",
        "lemma": "encontronazo",
        "upos": "NOUN",
        "xpos": "ncms000",
        "feats": "Gender=Masc|Number=Sing",
        "head": 6,
        "deprel": "obl:arg",
        "start_char": 43,
        "end_char": 55
      },
      {
        "id": 9,
        "text": "con",
        "lemma": "con",
        "upos": "ADP",
        "xpos": "sps00",
        "feats": null,
        "head": 11,
        "deprel": "case",
        "start_char": 56,
        "end_char": 59
      },
      {
        "id": 10,
        "text": "el",
        "lemma": "el",
        "upos": "DET",
        "xpos": "da0ms0",
        "feats": "Definite=Def|Gender=Masc|Number=Sing|PronType=Art",
        "head": 11,
        "deprel": "det",
        "start_char": 60,
        "end_char": 62
      },
      {
        "id": 11,
        "text": "Gobierno",
        "lemma": "gobierno",
        "upos": "PROPN",
        "xpos": "np00000",
        "feats": null,
        "head": 8,
        "deprel": "nmod",
        "start_char": 63,
        "end_char": 71
      },
      {
        "id": 12,
        "text": ".",
        "lemma": ".",
        "upos": "PUNCT",
        "xpos": "fp",
        "feats": "PunctType=Peri",
        "head": 6,
        "deprel": "punct",
        "start_char": 71,
        "end_char": 72
      }
    ]
  },
  {
    "sent_id": 2,
    "text": "El ministro de Presidencia, Félix Bolaños, le ha replicado por carta este mismo jueves mostrando su “sorpresa” y aludiendo directamente a la expresión “banda de ladrones”.",
    "tokens": [
      {
        "id": 1,
        "text": "El",
        "lemma": "el",
        "upos": "DET",
        "xpos": "da0ms0",
        "feats": "Definite=Def|Gender=Masc|Number=Sing|PronType=Art",
        "head": 2,
        "deprel": "det",
        "start_char": 73,
        "end_char": 75
      },
      {
        "id": 2,
        "text": "ministro",
        "lemma": "ministro",
        "upos": "NOUN",
        "xpos": "ncms000",
        "feats": "Gender=Masc|Number=Sing",
        "head": 11,
        "deprel": "nsubj",
        "start_char": 76,
        "end_char": 84
      },
      {
        "id": 3,
        "text": "de",
        "lemma": "de",
        "upos": "ADP",
        "xpos": "sps00",
        "feats": null,
        "head": 4,
        "deprel": "case",
        "start_char": 85,
        "end_char": 87
      },
      {
        "id": 4,
        "text": "Presidencia",
        "lemma": "Presidencia",
        "upos": "PROPN",
        "xpos": "np00000",
        "feats": null,
        "head": 2,
        "deprel": "nmod",
        "start_char": 88,
        "end_char": 99
      },
      {
        "id": 5,
        "text": ",",
        "lemma": ",",
        "upos": "PUNCT",
        "xpos": "fc",
        "feats": "PunctType=Comm",
        "head": 6,
        "deprel": "punct",
        "start_char": 99,
        "end_char": 100
      },
      {
        "id": 6,
        "text": "Félix",
        "lemma": "Félix",
        "upos": "PROPN",
        "xpos": "np00000",
        "feats": null,
        "head": 2,
        "deprel": "appos",
        "start_char": 101,
        "end_char": 106
      },
      {
        "id": 7,
        "text": "Bolaños",
        "lemma": "Bolaños",
        "upos": "PROPN",
        "xpos": null,
        "feats": null,
        "head": 6,
        "deprel": "flat",
        "start_char": 107,
        "end_char": 114
      },
      {
        "id": 8,
        "text": ",",
        "lemma": ",",
        "upos": "PUNCT",
        "xpos": "fc",
        "feats": "PunctType=Comm",
        "head": 6,
        "deprel": "punct",
        "start_char": 114,
        "end_char": 115
      },
      {
        "id": 9,
        "text": "le",
        "lemma": "él",
        "upos": "PRON",
        "xpos": "pp3csd00",
        "feats": "Case=Dat|Number=Sing|Person=3|PronType=Prs",
        "head": 11,
        "deprel": "expl",
        "start_char": 116,
        "end_char": 118
      },
      {
        "id": 10,
        "text": "ha",
        "lemma": "haber",
        "upos": "AUX",
        "xpos": "vaip3s0",
        "feats": "Mood=Ind|Number=Sing|Person=3|Tense=Pres|VerbForm=Fin",
        "head": 11,
        "deprel": "aux",
        "start_char": 119,
        "end_char": 121
      },
      {
        "id": 11,
        "text": "replicado",
        "lemma": "replicar",
        "upos": "VERB",
        "xpos": "vmp00sm",
        "feats": "Gender=Masc|Number=Sing|Tense=Past|VerbForm=Part",
        "head": 0,
        "deprel": "root",
        "start_char": 122,
        "end_char": 131
      },
      {
        "id": 12,
        "text": "por",
        "lemma": "por",
        "upos": "ADP",
        "xpos": "sps00",
        "feats": null,
        "head": 13,
        "deprel": "case",
        "start_char": 132,
        "end_char": 135
      },
      {
        "id": 13,
        "text": "carta",
        "lemma": "carta",
        "upos": "NOUN",
        "xpos": "ncfs000",
        "feats": "Gender=Fem|Number=Sing",
        "head": 11,
        "deprel": "obl",
        "start_char": 136,
        "end_char": 141
      },
      {
        "id": 14,
        "text": "este",
        "lemma": "este",
        "upos": "DET",
        "xpos": "dd0ms0",
        "feats": "Gender=Masc|Number=Sing|PronType=Dem",
        "head": 16,
        "deprel": "det",
        "start_char": 142,
        "end_char": 146
      },
      {
        "id": 15,
        "text": "mismo",
        "lemma": "mismo",
        "upos": "DET",
        "xpos": "di0ms0",
        "feats": "Gender=Masc|Number=Sing|PronType=Dem",
        "head": 16,
        "deprel": "amod",
        "start_char": 147,
        "end_char": 152
      },
      {
        "id": 16,
        "text": "jueves",
        "lemma": "jueves",
        "upos": "NOUN",
        "xpos": null,
        "feats": null,
        "head": 11,
        "deprel": "obl",
        "start_char": 153,
        "end_char": 159
      },
      {
        "id": 17,
        "text": "mostrando",
        "lemma": "mostrar",
        "upos": "VERB",
        "xpos": "vmg0000",
        "feats": "VerbForm=Ger",
        "head": 11,
        "deprel": "advcl",
        "start_char": 160,
        "end_char": 169
      },
      {
        "id": 18,
        "text": "su",
        "lemma": "su",
        "upos": "DET",
        "xpos": "dp3cs0",
        "feats": "Number=Sing|Person=3|Poss=Yes|PronType=Prs",
        "head": 20,
        "deprel": "det",
        "start_char": 170,
        "end_char": 172
      },
      {
        "id": 19,
        "text": "“",
        "lemma": "\"",
        "upos": "PUNCT",
        "xpos": "fe",
        "feats": "PunctType=Quot",
        "head": 20,
        "deprel": "punct",
        "start_char": 173,
        "end_char": 174
      },
      {
        "id": 20,
        "text": "sorpresa",
        "lemma": "sorpresa",
        "upos": "NOUN",
        "xpos": "ncfs000",
        "feats": "Gender=Fem|Number=Sing",
        "head": 17,
        "deprel": "obj",
        "start_char": 174,
        "end_char": 182
      },
      {
        "id": 21,
        "text": "”",
        "lemma": "\"",
        "upos": "PUNCT",
        "xpos": "fe",
        "feats": "PunctType=Quot",
        "head": 20,
        "deprel": "punct",
        "start_char": 182,
        "end_char": 183
      },
      {
        "id": 22,
        "text": "y",
        "lemma": "y",
        "upos": "CCONJ",
        "xpos": "cc",
        "feats": null,
        "head": 23,
        "deprel": "cc",
        "start_char": 184,
        "end_char": 185
      },
      {
        "id": 23,
        "text": "aludiendo",
        "lemma": "aludir",
        "upos": "VERB",
        "xpos": "vmg0000",
        "feats": "VerbForm=Ger",
        "head": 17,
        "deprel": "conj",
        "start_char": 186,
        "end_char": 195
      },
      {
        "id": 24,
        "text": "directamente",
        "lemma": "directamente",
        "upos": "ADV",
        "xpos": "rg",
        "feats": null,
        "head": 23,
        "deprel": "advmod",
        "start_char": 196,
        "end_char": 208
      },
      {
        "id": 25,
        "text": "a",
        "lemma": "a",
        "upos": "ADP",
        "xpos": "sps00",
        "feats": null,
        "head": 27,
        "deprel": "case",
        "start_char": 209,
        "end_char": 210
      },
      {
        "id": 26,
        "text": "la",
        "lemma": "el",
        "upos": "DET",
        "xpos": "da0fs0",
        "feats": "Definite=Def|Gender=Fem|Number=Sing|PronType=Art",
        "head": 27,
        "deprel": "det",
        "start_char": 211,
        "end_char": 213
      },
      {
        "id": 27,
        "text": "expresión",
        "lemma": "expresión",
        "upos": "NOUN",
        "xpos": "ncfs000",
        "feats": "Gender=Fem|Number=Sing",
        "head": 23,
        "deprel": "obl:arg",
        "start_char": 214,
        "end_char": 223
      },
      {
        "id": 28,
        "text": "“",
        "lemma": "\"",
        "upos": "PUNCT",
        "xpos": "fe",
        "feats": "PunctType=Quot",
        "head": 29,
        "deprel": "punct",
        "start_char": 224,
        "end_char": 225
      },
      {
        "id": 29,
        "text": "banda",
        "lemma": "banda",
        "upos": "NOUN",
        "xpos": "ncfs000",
        "feats": "Gender=Fem|Number=Sing",
        "head": 27,
        "deprel": "appos",
        "start_char": 225,
        "end_char": 230
      },
      {
        "id": 30,
        "text": "de",
        "lemma": "de",
        "upos": "ADP",
        "xpos": "sps00",
        "feats": null,
        "head": 31,
        "deprel": "case",
        "start_char": 231,
        "end_char": 233
      },
      {
        "id": 31,
        "text": "ladrones",
        "lemma": "ladrón",
        "upos": "NOUN",
        "xpos": "ncmp000",
        "feats": "Gender=Masc|Number=Plur",
        "head": 29,
        "deprel": "nmod",
        "start_char": 234,
        "end_char": 242
      },
      {
        "id": 32,
        "text": "”",
        "lemma": "\"",
        "upos": "PUNCT",
        "xpos": "fe",
        "feats": "PunctType=Quot",
        "head": 29,
        "deprel": "punct",
        "start_char": 242,
        "end_char": 243
      },
      {
        "id": 33,
        "text": ".",
        "lemma": ".",
        "upos": "PUNCT",
        "xpos": "fp",
        "feats": "PunctType=Peri",
        "head": 11,
        "deprel": "punct",
        "start_char": 243,
        "end_char": 244
      }
    ]
  },
  {
    "sent_id": 3,
    "text": "“Para mostrarle que su razonamiento no es solo injusto, sino profundamente contraproducente para la institución que usted preside, permítame hacerle una pregunta”, adelanta el ministro.",
    "tokens": [
      {
        "id": 1,
        "text": "“",
        "lemma": "\"",
        "upos": "PUNCT",
        "xpos": "fe",
        "feats": "PunctType=Quot",
        "head": 23,
        "deprel": "punct",
        "start_char": 245,
        "end_char": 246
      },
      {
        "id": 2,
        "text": "Para",
        "lemma": "para",
        "upos": "ADP",
        "xpos": "sps00",
        "feats": null,
        "head": 3,
        "deprel": "mark",
        "start_char": 246,
        "end_char": 250
      },
      {
        "id": 3,
        "text": "mostrar",
        "lemma": "mostrar",
        "upos": "VERB",
        "xpos": "vmn0000",
        "feats": "VerbForm=Inf",
        "head": 23,
        "deprel": "advcl",
        "start_char": 251,
        "end_char": 258
      },
      {
        "id": 4,
        "text": "le",
        "lemma": "él",
        "upos": "PRON",
        "xpos": null,
        "feats": "Case=Dat|Number=Sing|Person=3|PronType=Prs",
        "head": 3,
        "deprel": "obl:arg",
        "start_char": 258,
        "end_char": 260
      },
      {
        "id": 5,
        "text": "que",
        "lemma": "que",
        "upos": "SCONJ",
        "xpos": "cs",
        "feats": null,
        "head": 11,
        "deprel": "mark",
        "start_char": 261,
        "end_char": 264
      },
      {
        "id": 6,
        "text": "su",
        "lemma": "su",
        "upos": "DET",
        "xpos": "dp3cs0",
        "feats": "Number=Sing|Person=3|Poss=Yes|PronType=Prs",
        "head": 7,
        "deprel": "det",
        "start_char": 265,
        "end_char": 267
      },
      {
        "id": 7,
        "text": "razonamiento",
        "lemma": "razonamiento",
        "upos": "NOUN",
        "xpos": "ncms000",
        "feats": "Gender=Masc|Number=Sing",
        "head": 11,
        "deprel": "nsubj",
        "start_char": 268,
        "end_char": 280
      },
      {
        "id": 8,
        "text": "no",
        "lemma": "no",
        "upos": "ADV",
        "xpos": "rn",
        "feats": "Polarity=Neg",
        "head": 11,
        "deprel": "advmod",
        "start_char": 281,
        "end_char": 283
      },
      {
        "id": 9,
        "text": "es",
        "lemma": "ser",
        "upos": "AUX",
        "xpos": "vsip3s0",
        "feats": "Mood=Ind|Number=Sing|Person=3|Tense=Pres|VerbForm=Fin",
        "head": 11,
        "deprel": "cop",
        "start_char": 284,
        "end_char": 286
      },
      {
        "id": 10,
        "text": "solo",
        "lemma": "sólo",
        "upos": "ADV",
        "xpos": "rg",
        "feats": null,
        "head": 11,
        "deprel": "advmod",
        "start_char": 287,
        "end_char": 291
      },
      {
        "id": 11,
        "text": "injusto",
        "lemma": "injusto",
        "upos": "ADJ",
        "xpos": "aq0ms0",
        "feats": "Gender=Masc|Number=Sing",
        "head": 3,
        "deprel": "ccomp",
        "start_char": 292,
        "end_char": 299
      },
      {
        "id": 12,
        "text": ",",
        "lemma": ",",
        "upos": "PUNCT",
        "xpos": "fc",
        "feats": "PunctType=Comm",
        "head": 15,
        "deprel": "punct",
        "start_char": 299,
        "end_char": 300
      },
      {
        "id": 13,
        "text": "sino",
        "lemma": "sino",
        "upos": "CCONJ",
        "xpos": "cc",
        "feats": null,
        "head": 15,
        "deprel": "cc",
        "start_char": 301,
        "end_char": 305
      },
      {
        "id": 14,
        "text": "profundamente",
        "lemma": "profundamente",
        "upos": "ADV",
        "xpos": "rg",
        "feats": null,
        "head": 15,
        "deprel": "advmod",
        "start_char": 306,
        "end_char": 319
      },
      {
        "id": 15,
        "text": "contraproducente",
        "lemma": "contraproducente",
        "upos": "ADJ",
        "xpos": "aq0cs0",
        "feats": "Number=Sing",
        "head": 11,
        "deprel": "conj",
        "start_char": 320,
        "end_char": 336
      },
      {
        "id": 16,
        "text": "para",
        "lemma": "para",
        "upos": "ADP",
        "xpos": "sps00",
        "feats": null,
        "head": 18,
        "deprel": "case",
        "start_char": 337,
        "end_char": 341
      },
      {
        "id": 17,
        "text": "la",
        "lemma": "el",
        "upos": "DET",
        "xpos": "da0fs0",
        "feats": "Definite=Def|Gender=Fem|Number=Sing|PronType=Art",
        "head": 18,
        "deprel": "det",
        "start_char": 342,
        "end_char": 344
      },
      {
        "id": 18,
        "text": "institución",
        "lemma": "institución",
        "upos": "NOUN",
        "xpos": "ncfs000",
        "feats": "Gender=Fem|Number=Sing",
        "head": 15,
        "deprel": "nmod",
        "start_char": 345,
        "end_char": 356
      },
      {
        "id": 19,
        "text": "que",
        "lemma": "que",
        "upos": "PRON",
        "xpos": "pr0cn000",
        "feats": "PronType=Rel",
        "head": 21,
        "deprel": "obj",
        "start_char": 357,
        "end_char": 360
      },
      {
        "id": 20,
        "text": "usted",
        "lemma": "tú",
        "upos": "PRON",
        "xpos": "pp2cs00p",
        "feats": "Case=Acc,Nom|Number=Sing|Person=2|Polite=Form|PronType=Prs",
        "head": 21,
        "deprel": "nsubj",
        "start_char": 361,
        "end_char": 366
      },
      {
        "id": 21,
        "text": "preside",
        "lemma": "presidir",
        "upos": "VERB",
        "xpos": "vmip3s0",
        "feats": "Mood=Ind|Number=Sing|Person=3|Tense=Pres|VerbForm=Fin",
        "head": 18,
        "deprel": "acl",
        "start_char": 367,
        "end_char": 374
      },
      {
        "id": 22,
        "text": ",",
        "lemma": ",",
        "upos": "PUNCT",
        "xpos": "fc",
        "feats": "PunctType=Comm",
        "head": 3,
        "deprel": "punct",
        "start_char": 374,
        "end_char": 375
      },
      {
        "id": 23,
        "text": "permítame",
        "lemma": "permítamer",
        "upos": "VERB",
        "xpos": "vmip1s0",
        "feats": "Mood=Ind|Number=Sing|Person=1|Tense=Pres|VerbForm=Fin",
        "head": 30,
        "deprel": "ccomp",
        "start_char": 376,
        "end_char": 385
      },
      {
        "id": 24,
        "text": "hacer",
        "lemma": "hacer",
        "upos": "VERB",
        "xpos": "vmn0000",
        "feats": "VerbForm=Inf",
        "head": 23,
        "deprel": "xcomp",
        "start_char": 386,
        "end_char": 391
      },
      {
        "id": 25,
        "text": "le",
        "lemma": "él",
        "upos": "PRON",
        "xpos": null,
        "feats": "Case=Dat|Number=Sing|Person=3|PronType=Prs",
        "head": 24,
        "deprel": "obl:arg",
        "start_char": 391,
        "end_char": 393
      },
      {
        "id": 26,
        "text": "una",
        "lemma": "uno",
        "upos": "DET",
        "xpos": "di0fs0",
        "feats": "Definite=Ind|Gender=Fem|Number=Sing|PronType=Art",
        "head": 27,
        "deprel": "det",
        "start_char": 394,
        "end_char": 397
      },
      {
        "id": 27,
        "text": "pregunta",
        "lemma": "pregunta",
        "upos": "NOUN",
        "xpos": "ncfs000",
        "feats": "Gender=Fem|Number=Sing",
        "head": 24,
        "deprel": "obj",
        "start_char": 398,
        "end_char": 406
      },
      {
        "id": 28,
        "text": "”",
        "lemma": "\"",
        "upos": "PUNCT",
        "xpos": "fe",
        "feats": "PunctType=Quot",
        "head": 23,
        "deprel": "punct",
        "start_char": 406,
        "end_char": 407
      },
      {
        "id": 29,
        "text": ",",
        "lemma": ",",
        "upos": "PUNCT",
        "xpos": "fc",
        "feats": "PunctType=Comm",
        "head": 23,
        "deprel": "punct",
        "start_char": 407,
        "end_char": 408
      },
      {
        "id": 30,
        "text": "adelanta",
        "lemma": "adelantar",
        "upos": "VERB",
        "xpos": "vmip3s0",
        "feats": "Mood=Ind|Number=Sing|Person=3|Tense=Pres|VerbForm=Fin",
        "head": 0,
        "deprel": "root",
        "start_char": 409,
        "end_char": 417
      },
      {
        "id": 31,
        "text": "el",
        "lemma": "el",
        "upos": "DET",
        "xpos": "da0ms0",
        "feats": "Definite=Def|Gender=Masc|Number=Sing|PronType=Art",
        "head": 32,
        "deprel": "det",
        "start_char": 418,
        "end_char": 420
      },
      {
        "id": 32,
        "text": "ministro",
        "lemma": "ministro",
        "upos": "NOUN",
        "xpos": "ncms000",
        "feats": "Gender=Masc|Number=Sing",
        "head": 30,
        "deprel": "nsubj",
        "start_char": 421,
        "end_char": 429
      },
      {
        "id": 33,
        "text": ".",
        "lemma": ".",
        "upos": "PUNCT",
        "xpos": "fp",
        "feats": "PunctType=Peri",
        "head": 30,
        "deprel": "punct",
        "start_char": 429,
        "end_char": 430
      }
    ]
  },
  {
    "sent_id": 4,
    "text": "“¿Qué le parecería si un miembro del Gobierno calificase a la Iglesia entera como 'banda de agresores sexuales, a las pruebas me remito?",
    "tokens": [
      {
        "id": 1,
        "text": "“",
        "lemma": "\"",
        "upos": "PUNCT",
        "xpos": "fe",
        "feats": "PunctType=Quot",
        "head": 5,
        "deprel": "punct",
        "start_char": 431,
        "end_char": 432
      },
      {
        "id": 2,
        "text": "¿",
        "lemma": "¿",
        "upos": "PUNCT",
        "xpos": "fia",
        "feats": "PunctSide=Ini|PunctType=Qest",
        "head": 5,
        "deprel": "punct",
        "start_char": 432,
        "end_char": 433
      },
      {
        "id": 3,
        "text": "Qué",
        "lemma": "qué",
        "upos": "PRON",
        "xpos": "pt0cs000",
        "feats": "Number=Sing|PronType=Int",
        "head": 5,
        "deprel": "nsubj",
        "start_char": 433,
        "end_char": 436
      },
      {
        "id": 4,
        "text": "le",
        "lemma": "él",
        "upos": "PRON",
        "xpos": "pp3csd00",
        "feats": "Case=Dat|Number=Sing|Person=3|PronType=Prs",
        "head": 5,
        "deprel": "obl:arg",
        "start_char": 437,
        "end_char": 439
      },
      {
        "id": 5,
        "text": "parecería",
        "lemma": "parecer",
        "upos": "VERB",
        "xpos": "vmic3s0",
        "feats": "Mood=Cnd|Number=Sing|Person=3|VerbForm=Fin",
        "head": 0,
        "deprel": "root",
        "start_char": 440,
        "end_char": 449
      },
      {
        "id": 6,
        "text": "si",
        "lemma": "si",
        "upos": "SCONJ",
        "xpos": "cs",
        "feats": null,
        "head": 12,
        "deprel": "mark",
        "start_char": 450,
        "end_char": 452
      },
      {
        "id": 7,
        "text": "un",
        "lemma": "uno",
        "upos": "DET",
        "xpos": "di0ms0",
        "feats": "Definite=Ind|Gender=Masc|Number=Sing|PronType=Art",
        "head": 8,
        "deprel": "det",
        "start_char": 453,
        "end_char": 455
      },
      {
        "id": 8,
        "text": "miembro",
        "lemma": "miembro",
        "upos": "NOUN",
        "xpos": "ncms000",
        "feats": "Gender=Masc|Number=Sing",
        "head": 12,
        "deprel": "nsubj",
        "start_char": 456,
        "end_char": 463
      },
      {
        "id": 9,
        "text": "de",
        "lemma": "de",
        "upos": "ADP",
        "xpos": "spcms",
        "feats": null,
        "head": 11,
        "deprel": "case",
        "start_char": null,
        "end_char": null
      },
      {
        "id": 10,
        "text": "el",
        "lemma": "el",
        "upos": "DET",
        "xpos": null,
        "feats": "Definite=Def|Gender=Masc|Number=Sing|PronType=Art",
        "head": 11,
        "deprel": "det",
        "start_char": null,
        "end_char": null
      },
      {
        "id": 11,
        "text": "Gobierno",
        "lemma": "gobierno",
        "upos": "PROPN",
        "xpos": "np00000",
        "feats": null,
        "head": 8,
        "deprel": "nmod",
        "start_char": 468,
        "end_char": 476
      },
      {
        "id": 12,
        "text": "calificase",
        "lemma": "calificar",
        "upos": "VERB",
        "xpos": "vmsi3s0",
        "feats": "Mood=Sub|Number=Sing|Person=3|Tense=Imp|VerbForm=Fin",
        "head": 5,
        "deprel": "csubj",
        "start_char": 477,
        "end_char": 487
      },
      {
        "id": 13,
        "text": "a",
        "lemma": "a",
        "upos": "ADP",
        "xpos": "sps00",
        "feats": null,
        "head": 15,
        "deprel": "case",
        "start_char": 488,
        "end_char": 489
      },
      {
        "id": 14,
        "text": "la",
        "lemma": "el",
        "upos": "DET",
        "xpos": "da0fs0",
        "feats": "Definite=Def|Gender=Fem|Number=Sing|PronType=Art",
        "head": 15,
        "deprel": "det",
        "start_char": 490,
        "end_char": 492
      },
      {
        "id": 15,
        "text": "Iglesia",
        "lemma": "Iglesia",
        "upos": "PROPN",
        "xpos": "np00000",
        "feats": null,
        "head": 12,
        "deprel": "obj",
        "start_char": 493,
        "end_char": 500
      },
      {
        "id": 16,
        "text": "entera",
        "lemma": "entero",
        "upos": "ADJ",
        "xpos": "aq0fs0",
        "feats": "Gender=Fem|Number=Sing",
        "head": 15,
        "deprel": "amod",
        "start_char": 501,
        "end_char": 507
      },
      {
        "id": 17,
        "text": "como",
        "lemma": "como",
        "upos": "SCONJ",
        "xpos": "cs",
        "feats": null,
        "head": 19,
        "deprel": "mark",
        "start_char": 508,
        "end_char": 512
      },
      {
        "id": 18,
        "text": "'",
        "lemma": "'",
        "upos": "PUNCT",
        "xpos": "fe",
        "feats": "PunctType=Quot",
        "head": 19,
        "deprel": "punct",
        "start_char": 513,
        "end_char": 514
      },
      {
        "id": 19,
        "text": "banda",
        "lemma": "banda",
        "upos": "NOUN",
        "xpos": "ncfs000",
        "feats": "Gender=Fem|Number=Sing",
        "head": 12,
        "deprel": "obl",
        "start_char": 514,
        "end_char": 519
      },
      {
        "id": 20,
        "text": "de",
        "lemma": "de",
        "upos": "ADP",
        "xpos": "sps00",
        "feats": null,
        "head": 21,
        "deprel": "case",
        "start_char": 520,
        "end_char": 522
      },
      {
        "id": 21,
        "text": "agresores",
        "lemma": "agresor",
        "upos": "NOUN",
        "xpos": "ncmp000",
        "feats": "Gender=Masc|Number=Plur",
        "head": 19,
        "deprel": "nmod",
        "start_char": 523,
        "end_char": 532
      },
      {
        "id": 22,
        "text": "sexuales",
        "lemma": "sexual",
        "upos": "ADJ",
        "xpos": "aq0cp0",
        "feats": "Number=Plur",
        "head": 21,
        "deprel": "amod",
        "start_char": 533,
        "end_char": 541
      },
      {
        "id": 23,
        "text": ",",
        "lemma": ",",
        "upos": "PUNCT",
        "xpos": "fc",
        "feats": "PunctType=Comm",
        "head": 28,
        "deprel": "punct",
        "start_char": 541,
        "end_char": 542
      },
      {
        "id": 24,
        "text": "a",
        "lemma": "a",
        "upos": "ADP",
        "xpos": "sps00",
        "feats": null,
        "head": 26,
        "deprel": "case",
        "start_char": 543,
        "end_char": 544
      },
      {
        "id": 25,
        "text": "las",
        "lemma": "el",
        "upos": "DET",
        "xpos": "da0fp0",
        "feats": "Definite=Def|Gender=Fem|Number=Plur|PronType=Art",
        "head": 26,
        "deprel": "det",
        "start_char": 545,
        "end_char": 548
      },
      {
        "id": 26,
        "text": "pruebas",
        "lemma": "prueba",
        "upos": "NOUN",
        "xpos": "ncfp000",
        "feats": "Gender=Fem|Number=Plur",
        "head": 28,
        "deprel": "obl:arg",
        "start_char": 549,
        "end_char": 556
      },
      {
        "id": 27,
        "text": "me",
        "lemma": "yo",
        "upos": "PRON",
        "xpos": "pp1cs000",
        "feats": "Case=Dat|Number=Sing|Person=1|PrepCase=Npr|PronType=Prs",
        "head": 28,
        "deprel": "obj",
        "start_char": 557,
        "end_char": 559
      },
      {
        "id": 28,
        "text": "remito",
        "lemma": "remitar",
        "upos": "VERB",
        "xpos": "vmip1s0",
        "feats": "Mood=Ind|Number=Sing|Person=1|Tense=Pres|VerbForm=Fin",
        "head": 5,
        "deprel": "parataxis",
        "start_char": 560,
        "end_char": 566
      },
      {
        "id": 29,
        "text": "?",
        "lemma": "?",
        "upos": "PUNCT",
        "xpos": "fit",
        "feats": "PunctSide=Fin|PunctType=Qest",
        "head": 5,
        "deprel": "punct",
        "start_char": 566,
        "end_char": 567
      }
    ]
  },
  {
    "sent_id": 5,
    "text": "Evidentemente sería falso y profundamente injusto”, le dice.",
    "tokens": [
      {
        "id": 1,
        "text": "Evidentemente",
        "lemma": "evidentemente",
        "upos": "ADV",
        "xpos": "rg",
        "feats": null,
        "head": 3,
        "deprel": "advmod",
        "start_char": 568,
        "end_char": 581
      },
      {
        "id": 2,
        "text": "sería",
        "lemma": "ser",
        "upos": "AUX",
        "xpos": "vsic3s0",
        "feats": "Mood=Cnd|Number=Sing|Person=3|VerbForm=Fin",
        "head": 3,
        "deprel": "cop",
        "start_char": 582,
        "end_char": 587
      },
      {
        "id": 3,
        "text": "falso",
        "lemma": "falso",
        "upos": "ADJ",
        "xpos": "aq0ms0",
        "feats": "Gender=Masc|Number=Sing",
        "head": 10,
        "deprel": "ccomp",
        "start_char": 588,
        "end_char": 593
      },
      {
        "id": 4,
        "text": "y",
        "lemma": "y",
        "upos": "CCONJ",
        "xpos": "cc",
        "feats": null,
        "head": 6,
        "deprel": "cc",
        "start_char": 594,
        "end_char": 595
      },
      {
        "id": 5,
        "text": "profundamente",
        "lemma": "profundamente",
        "upos": "ADV",
        "xpos": "rg",
        "feats": null,
        "head": 6,
        "deprel": "advmod",
        "start_char": 596,
        "end_char": 609
      },
      {
        "id": 6,
        "text": "injusto",
        "lemma": "injusto",
        "upos": "ADJ",
        "xpos": "aq0ms0",
        "feats": "Gender=Masc|Number=Sing",
        "head": 3,
        "deprel": "conj",
        "start_char": 610,
        "end_char": 617
      },
      {
        "id": 7,
        "text": "”",
        "lemma": "\"",
        "upos": "PUNCT",
        "xpos": "fe",
        "feats": "PunctType=Quot",
        "head": 3,
        "deprel": "punct",
        "start_char": 617,
        "end_char": 618
      },
      {
        "id": 8,
        "text": ",",
        "lemma": ",",
        "upos": "PUNCT",
        "xpos": "fc",
        "feats": "PunctType=Comm",
        "head": 3,
        "deprel": "punct",
        "start_char": 618,
        "end_char": 619
      },
      {
        "id": 9,
        "text": "le",
        "lemma": "él",
        "upos": "PRON",
        "xpos": "pp3csd00",
        "feats": "Case=Dat|Number=Sing|Person=3|PronType=Prs",
        "head": 10,
        "deprel": "obl:arg",
        "start_char": 620,
        "end_char": 622
      },
      {
        "id": 10,
        "text": "dice",
        "lemma": "decir",
        "upos": "VERB",
        "xpos": "vmip3s0",
        "feats": "Mood=Ind|Number=Sing|Person=3|Tense=Pres|VerbForm=Fin",
        "head": 0,
        "deprel": "root",
        "start_char": 623,
        "end_char": 627
      },
      {
        "id": 11,
        "text": ".",
        "lemma": ".",
        "upos": "PUNCT",
        "xpos": "fp",
        "feats": "PunctType=Peri",
        "head": 10,
        "deprel": "punct",
        "start_char": 627,
        "end_char": 628
      }
    ]
  },
  {
    "sent_id": 6,
    "text": "Bolaños ha instado al prelado a que las relaciones de la Conferencia Episcopal con el Gobierno estén “marcadas por la moderación, el respeto y la justicia en lugar de por la exageración y el partidismo en favor de las fuerzas de la derecha y la ultraderecha”, y le ha recordado unas palabras que atribuye a León XIV en su reciente viaje apostólico a España: “Quienes ejercen una responsabilidad pública tienen una especial obligación de custodiar la palabra para desarmar el lenguaje”.",
    "tokens": [
      {
        "id": 1,
        "text": "Bolaños",
        "lemma": "Bolaños",
        "upos": "PROPN",
        "xpos": "np00000",
        "feats": null,
        "head": 3,
        "deprel": "nsubj",
        "start_char": 629,
        "end_char": 636
      },
      {
        "id": 2,
        "text": "ha",
        "lemma": "haber",
        "upos": "AUX",
        "xpos": "vaip3s0",
        "feats": "Mood=Ind|Number=Sing|Person=3|Tense=Pres|VerbForm=Fin",
        "head": 3,
        "deprel": "aux",
        "start_char": 637,
        "end_char": 639
      },
      {
        "id": 3,
        "text": "instado",
        "lemma": "instar",
        "upos": "VERB",
        "xpos": "vmp00sm",
        "feats": "Gender=Masc|Number=Sing|Tense=Past|VerbForm=Part",
        "head": 0,
        "deprel": "root",
        "start_char": 640,
        "end_char": 647
      },
      {
        "id": 4,
        "text": "a",
        "lemma": "a",
        "upos": "ADP",
        "xpos": "spcms",
        "feats": null,
        "head": 6,
        "deprel": "case",
        "start_char": null,
        "end_char": null
      },
      {
        "id": 5,
        "text": "el",
        "lemma": "el",
        "upos": "DET",
        "xpos": null,
        "feats": "Definite=Def|Gender=Masc|Number=Sing|PronType=Art",
        "head": 6,
        "deprel": "det",
        "start_char": null,
        "end_char": null
      },
      {
        "id": 6,
        "text": "prelado",
        "lemma": "prelado",
        "upos": "NOUN",
        "xpos": "ncms000",
        "feats": "Gender=Masc|Number=Sing",
        "head": 3,
        "deprel": "obl:arg",
        "start_char": 651,
        "end_char": 658
      },
      {
        "id": 7,
        "text": "a",
        "lemma": "a",
        "upos": "ADP",
        "xpos": "sps00",
        "feats": null,
        "head": 20,
        "deprel": "mark",
        "start_char": 659,
        "end_char": 660
      },
      {
        "id": 8,
        "text": "que",
        "lemma": "que",
        "upos": "SCONJ",
        "xpos": "cs",
        "feats": null,
        "head": 20,
        "deprel": "mark",
        "start_char": 661,
        "end_char": 664
      },
      {
        "id": 9,
        "text": "las",
        "lemma": "el",
        "upos": "DET",
        "xpos": "da0fp0",
        "feats": "Definite=Def|Gender=Fem|Number=Plur|PronType=Art",
        "head": 10,
        "deprel": "det",
        "start_char": 665,
        "end_char": 668
      },
      {
        "id": 10,
        "text": "relaciones",
        "lemma": "relación",
        "upos": "NOUN",
        "xpos": "ncfp000",
        "feats": "Gender=Fem|Number=Plur",
        "head": 20,
        "deprel": "nsubj",
        "start_char": 669,
        "end_char": 679
      },
      {
        "id": 11,
        "text": "de",
        "lemma": "de",
        "upos": "ADP",
        "xpos": "sps00",
        "feats": null,
        "head": 13,
        "deprel": "case",
        "start_char": 680,
        "end_char": 682
      },
      {
        "id": 12,
        "text": "la",
        "lemma": "el",
        "upos": "DET",
        "xpos": "da0fs0",
        "feats": "Definite=Def|Gender=Fem|Number=Sing|PronType=Art",
        "head": 13,
        "deprel": "det",
        "start_char": 683,
        "end_char": 685
      },
      {
        "id": 13,
        "text": "Conferencia",
        "lemma": "Conferencia",
        "upos": "PROPN",
        "xpos": "np00000",
        "feats": null,
        "head": 10,
        "deprel": "nmod",
        "start_char": 686,
        "end_char": 697
      },
      {
        "id": 14,
        "text": "Episcopal",
        "lemma": "Episcopal",
        "upos": "PROPN",
        "xpos": null,
        "feats": null,
        "head": 13,
        "deprel": "flat",
        "start_char": 698,
        "end_char": 707
      },
      {
        "id": 15,
        "text": "con",
        "lemma": "con",
        "upos": "ADP",
        "xpos": "sps00",
        "feats": null,
        "head": 17,
        "deprel": "case",
        "start_char": 708,
        "end_char": 711
      },
      {
        "id": 16,
        "text": "el",
        "lemma": "el",
        "upos": "DET",
        "xpos": "da0ms0",
        "feats": "Definite=Def|Gender=Masc|Number=Sing|PronType=Art",
        "head": 17,
        "deprel": "det",
        "start_char": 712,
        "end_char": 714
      },
      {
        "id": 17,
        "text": "Gobierno",
        "lemma": "gobierno",
        "upos": "PROPN",
        "xpos": "np00000",
        "feats": null,
        "head": 10,
        "deprel": "nmod",
        "start_char": 715,
        "end_char": 723
      },
      {
        "id": 18,
        "text": "estén",
        "lemma": "estar",
        "upos": "AUX",
        "xpos": "vmsp3p0",
        "feats": "Mood=Sub|Number=Plur|Person=3|Tense=Pres|VerbForm=Fin",
        "head": 20,
        "deprel": "cop",
        "start_char": 724,
        "end_char": 729
      },
      {
        "id": 19,
        "text": "“",
        "lemma": "\"",
        "upos": "PUNCT",
        "xpos": "fe",
        "feats": "PunctType=Quot",
        "head": 20,
        "deprel": "punct",
        "start_char": 730,
        "end_char": 731
      },
      {
        "id": 20,
        "text": "marcadas",
        "lemma": "marcado",
        "upos": "ADJ",
        "xpos": "aq0fpp",
        "feats": "Gender=Fem|Number=Plur|VerbForm=Part",
        "head": 3,
        "deprel": "ccomp",
        "start_char": 731,
        "end_char": 739
      },
      {
        "id": 21,
        "text": "por",
        "lemma": "por",
        "upos": "ADP",
        "xpos": "sps00",
        "feats": null,
        "head": 23,
        "deprel": "case",
        "start_char": 740,
        "end_char": 743
      },
      {
        "id": 22,
        "text": "la",
        "lemma": "el",
        "upos": "DET",
        "xpos": "da0fs0",
        "feats": "Definite=Def|Gender=Fem|Number=Sing|PronType=Art",
        "head": 23,
        "deprel": "det",
        "start_char": 744,
        "end_char": 746
      },
      {
        "id": 23,
        "text": "moderación",
        "lemma": "moderación",
        "upos": "NOUN",
        "xpos": "ncfs000",
        "feats": "Gender=Fem|Number=Sing",
        "head": 20,
        "deprel": "obl:agent",
        "start_char": 747,
        "end_char": 757
      },
      {
        "id": 24,
        "text": ",",
        "lemma": ",",
        "upos": "PUNCT",
        "xpos": "fc",
        "feats": "PunctType=Comm",
        "head": 26,
        "deprel": "punct",
        "start_char": 757,
        "end_char": 758
      },
      {
        "id": 25,
        "text": "el",
        "lemma": "el",
        "upos": "DET",
        "xpos": "da0ms0",
        "feats": "Definite=Def|Gender=Masc|Number=Sing|PronType=Art",
        "head": 26,
        "deprel": "det",
        "start_char": 759,
        "end_char": 761
      },
      {
        "id": 26,
        "text": "respeto",
        "lemma": "respeto",
        "upos": "NOUN",
        "xpos": "ncms000",
        "feats": "Gender=Masc|Number=Sing",
        "head": 23,
        "deprel": "appos",
        "start_char": 762,
        "end_char": 769
      },
      {
        "id": 27,
        "text": "y",
        "lemma": "y",
        "upos": "CCONJ",
        "xpos": "cc",
        "feats": null,
        "head": 29,
        "deprel": "cc",
        "start_char": 770,
        "end_char": 771
      },
      {
        "id": 28,
        "text": "la",
        "lemma": "el",
        "upos": "DET",
        "xpos": "da0fs0",
        "feats": "Definite=Def|Gender=Fem|Number=Sing|PronType=Art",
        "head": 29,
        "deprel": "det",
        "start_char": 772,
        "end_char": 774
      },
      {
        "id": 29,
        "text": "justicia",
        "lemma": "justicia",
        "upos": "NOUN",
        "xpos": "ncfs000",
        "feats": "Gender=Fem|Number=Sing",
        "head": 23,
        "deprel": "conj",
        "start_char": 775,
        "end_char": 783
      },
      {
        "id": 30,
        "text": "en",
        "lemma": "en",
        "upos": "ADP",
        "xpos": "sps00",
        "feats": null,
        "head": 35,
        "deprel": "case",
        "start_char": 784,
        "end_char": 786
      },
      {
        "id": 31,
        "text": "lugar",
        "lemma": "lugar",
        "upos": "NOUN",
        "xpos": null,
        "feats": null,
        "head": 30,
        "deprel": "fixed",
        "start_char": 787,
        "end_char": 792
      },
      {
        "id": 32,
        "text": "de",
        "lemma": "de",
        "upos": "ADP",
        "xpos": null,
        "feats": null,
        "head": 30,
        "deprel": "fixed",
        "start_char": 793,
        "end_char": 795
      },
      {
        "id": 33,
        "text": "por",
        "lemma": "por",
        "upos": "ADP",
        "xpos": "sps00",
        "feats": null,
        "head": 35,
        "deprel": "case",
        "start_char": 796,
        "end_char": 799
      },
      {
        "id": 34,
        "text": "la",
        "lemma": "el",
        "upos": "DET",
        "xpos": "da0fs0",
        "feats": "Definite=Def|Gender=Fem|Number=Sing|PronType=Art",
        "head": 35,
        "deprel": "det",
        "start_char": 800,
        "end_char": 802
      },
      {
        "id": 35,
        "text": "exageración",
        "lemma": "exageración",
        "upos": "NOUN",
        "xpos": "ncfs000",
        "feats": "Gender=Fem|Number=Sing",
        "head": 20,
        "deprel": "obl",
        "start_char": 803,
        "end_char": 814
      },
      {
        "id": 36,
        "text": "y",
        "lemma": "y",
        "upos": "CCONJ",
        "xpos": "cc",
        "feats": null,
        "head": 38,
        "deprel": "cc",
        "start_char": 815,
        "end_char": 816
      },
      {
        "id": 37,
        "text": "el",
        "lemma": "el",
        "upos": "DET",
        "xpos": "da0ms0",
        "feats": "Definite=Def|Gender=Masc|Number=Sing|PronType=Art",
        "head": 38,
        "deprel": "det",
        "start_char": 817,
        "end_char": 819
      },
      {
        "id": 38,
        "text": "partidismo",
        "lemma": "partidismo",
        "upos": "NOUN",
        "xpos": "ncms000",
        "feats": "Gender=Masc|Number=Sing",
        "head": 35,
        "deprel": "conj",
        "start_char": 820,
        "end_char": 830
      },
      {
        "id": 39,
        "text": "en",
        "lemma": "en",
        "upos": "ADP",
        "xpos": "sps00",
        "feats": null,
        "head": 43,
        "deprel": "case",
        "start_char": 831,
        "end_char": 833
      },
      {
        "id": 40,
        "text": "favor",
        "lemma": "favor",
        "upos": "NOUN",
        "xpos": null,
        "feats": null,
        "head": 39,
        "deprel": "fixed",
        "start_char": 834,
        "end_char": 839
      },
      {
        "id": 41,
        "text": "de",
        "lemma": "de",
        "upos": "ADP",
        "xpos": null,
        "feats": null,
        "head": 39,
        "deprel": "fixed",
        "start_char": 840,
        "end_char": 842
      },
      {
        "id": 42,
        "text": "las",
        "lemma": "el",
        "upos": "DET",
        "xpos": "da0fp0",
        "feats": "Definite=Def|Gender=Fem|Number=Plur|PronType=Art",
        "head": 43,
        "deprel": "det",
        "start_char": 843,
        "end_char": 846
      },
      {
        "id": 43,
        "text": "fuerzas",
        "lemma": "fuerza",
        "upos": "NOUN",
        "xpos": "ncfp000",
        "feats": "Gender=Fem|Number=Plur",
        "head": 35,
        "deprel": "nmod",
        "start_char": 847,
        "end_char": 854
      },
      {
        "id": 44,
        "text": "de",
        "lemma": "de",
        "upos": "ADP",
        "xpos": "sps00",
        "feats": null,
        "head": 46,
        "deprel": "case",
        "start_char": 855,
        "end_char": 857
      },
      {
        "id": 45,
        "text": "la",
        "lemma": "el",
        "upos": "DET",
        "xpos": "da0fs0",
        "feats": "Definite=Def|Gender=Fem|Number=Sing|PronType=Art",
        "head": 46,
        "deprel": "det",
        "start_char": 858,
        "end_char": 860
      },
      {
        "id": 46,
        "text": "derecha",
        "lemma": "derecha",
        "upos": "NOUN",
        "xpos": "ncfs000",
        "feats": "Gender=Fem|Number=Sing",
        "head": 43,
        "deprel": "nmod",
        "start_char": 861,
        "end_char": 868
      },
      {
        "id": 47,
        "text": "y",
        "lemma": "y",
        "upos": "CCONJ",
        "xpos": "cc",
        "feats": null,
        "head": 49,
        "deprel": "cc",
        "start_char": 869,
        "end_char": 870
      },
      {
        "id": 48,
        "text": "la",
        "lemma": "el",
        "upos": "DET",
        "xpos": "da0fs0",
        "feats": "Definite=Def|Gender=Fem|Number=Sing|PronType=Art",
        "head": 49,
        "deprel": "det",
        "start_char": 871,
        "end_char": 873
      },
      {
        "id": 49,
        "text": "ultraderecha",
        "lemma": "ultraderecha",
        "upos": "NOUN",
        "xpos": "ncfs000",
        "feats": "Gender=Fem|Number=Sing",
        "head": 23,
        "deprel": "conj",
        "start_char": 874,
        "end_char": 886
      },
      {
        "id": 50,
        "text": "”",
        "lemma": "\"",
        "upos": "PUNCT",
        "xpos": "fe",
        "feats": "PunctType=Quot",
        "head": 20,
        "deprel": "punct",
        "start_char": 886,
        "end_char": 887
      },
      {
        "id": 51,
        "text": ",",
        "lemma": ",",
        "upos": "PUNCT",
        "xpos": "fc",
        "feats": "PunctType=Comm",
        "head": 55,
        "deprel": "punct",
        "start_char": 887,
        "end_char": 888
      },
      {
        "id": 52,
        "text": "y",
        "lemma": "y",
        "upos": "CCONJ",
        "xpos": "cc",
        "feats": null,
        "head": 55,
        "deprel": "cc",
        "start_char": 889,
        "end_char": 890
      },
      {
        "id": 53,
        "text": "le",
        "lemma": "él",
        "upos": "PRON",
        "xpos": "pp3csd00",
        "feats": "Case=Dat|Number=Sing|Person=3|PronType=Prs",
        "head": 55,
        "deprel": "obl:arg",
        "start_char": 891,
        "end_char": 893
      },
      {
        "id": 54,
        "text": "ha",
        "lemma": "haber",
        "upos": "AUX",
        "xpos": "vaip3s0",
        "feats": "Mood=Ind|Number=Sing|Person=3|Tense=Pres|VerbForm=Fin",
        "head": 55,
        "deprel": "aux",
        "start_char": 894,
        "end_char": 896
      },
      {
        "id": 55,
        "text": "recordado",
        "lemma": "recordar",
        "upos": "VERB",
        "xpos": "vmp00sm",
        "feats": "Gender=Masc|Number=Sing|Tense=Past|VerbForm=Part",
        "head": 3,
        "deprel": "conj",
        "start_char": 897,
        "end_char": 906
      },
      {
        "id": 56,
        "text": "unas",
        "lemma": "uno",
        "upos": "DET",
        "xpos": "di0fp0",
        "feats": "Definite=Ind|Gender=Fem|Number=Plur|PronType=Art",
        "head": 57,
        "deprel": "det",
        "start_char": 907,
        "end_char": 911
      },
      {
        "id": 57,
        "text": "palabras",
        "lemma": "palabra",
        "upos": "NOUN",
        "xpos": "ncfp000",
        "feats": "Gender=Fem|Number=Plur",
        "head": 55,
        "deprel": "obj",
        "start_char": 912,
        "end_char": 920
      },
      {
        "id": 58,
        "text": "que",
        "lemma": "que",
        "upos": "PRON",
        "xpos": "pr0cn000",
        "feats": "PronType=Rel",
        "head": 59,
        "deprel": "obj",
        "start_char": 921,
        "end_char": 924
      },
      {
        "id": 59,
        "text": "atribuye",
        "lemma": "atribuir",
        "upos": "VERB",
        "xpos": "vmip3s0",
        "feats": "Mood=Ind|Number=Sing|Person=3|Tense=Pres|VerbForm=Fin",
        "head": 57,
        "deprel": "acl",
        "start_char": 925,
        "end_char": 933
      },
      {
        "id": 60,
        "text": "a",
        "lemma": "a",
        "upos": "ADP",
        "xpos": "sps00",
        "feats": null,
        "head": 61,
        "deprel": "case",
        "start_char": 934,
        "end_char": 935
      },
      {
        "id": 61,
        "text": "León",
        "lemma": "León",
        "upos": "PROPN",
        "xpos": "np00000",
        "feats": null,
        "head": 59,
        "deprel": "obl:arg",
        "start_char": 936,
        "end_char": 940
      },
      {
        "id": 62,
        "text": "XIV",
        "lemma": "xiv",
        "upos": "NUM",
        "xpos": null,
        "feats": "NumForm=Roman|NumType=Card",
        "head": 61,
        "deprel": "flat",
        "start_char": 941,
        "end_char": 944
      },
      {
        "id": 63,
        "text": "en",
        "lemma": "en",
        "upos": "ADP",
        "xpos": "sps00",
        "feats": null,
        "head": 66,
        "deprel": "case",
        "start_char": 945,
        "end_char": 947
      },
      {
        "id": 64,
        "text": "su",
        "lemma": "su",
        "upos": "DET",
        "xpos": "dp3cs0",
        "feats": "Number=Sing|Person=3|Poss=Yes|PronType=Prs",
        "head": 66,
        "deprel": "det",
        "start_char": 948,
        "end_char": 950
      },
      {
        "id": 65,
        "text": "reciente",
        "lemma": "reciente",
        "upos": "ADJ",
        "xpos": "aq0cs0",
        "feats": "Number=Sing",
        "head": 66,
        "deprel": "amod",
        "start_char": 951,
        "end_char": 959
      },
      {
        "id": 66,
        "text": "viaje",
        "lemma": "viaje",
        "upos": "NOUN",
        "xpos": "ncms000",
        "feats": "Gender=Masc|Number=Sing",
        "head": 59,
        "deprel": "obl",
        "start_char": 960,
        "end_char": 965
      },
      {
        "id": 67,
        "text": "apostólico",
        "lemma": "apostólico",
        "upos": "ADJ",
        "xpos": "aq0ms0",
        "feats": "Gender=Masc|Number=Sing",
        "head": 66,
        "deprel": "amod",
        "start_char": 966,
        "end_char": 976
      },
      {
        "id": 68,
        "text": "a",
        "lemma": "a",
        "upos": "ADP",
        "xpos": "sps00",
        "feats": null,
        "head": 69,
        "deprel": "case",
        "start_char": 977,
        "end_char": 978
      },
      {
        "id": 69,
        "text": "España",
        "lemma": "España",
        "upos": "PROPN",
        "xpos": "np00000",
        "feats": null,
        "head": 66,
        "deprel": "nmod",
        "start_char": 979,
        "end_char": 985
      },
      {
        "id": 70,
        "text": ":",
        "lemma": ":",
        "upos": "PUNCT",
        "xpos": "fd",
        "feats": "PunctType=Colo",
        "head": 77,
        "deprel": "punct",
        "start_char": 985,
        "end_char": 986
      },
      {
        "id": 71,
        "text": "“",
        "lemma": "\"",
        "upos": "PUNCT",
        "xpos": "fe",
        "feats": "PunctType=Quot",
        "head": 77,
        "deprel": "punct",
        "start_char": 987,
        "end_char": 988
      },
      {
        "id": 72,
        "text": "Quienes",
        "lemma": "quien",
        "upos": "PRON",
        "xpos": "pr0cp000",
        "feats": "Number=Plur|PronType=Rel",
        "head": 73,
        "deprel": "nsubj",
        "start_char": 988,
        "end_char": 995
      },
      {
        "id": 73,
        "text": "ejercen",
        "lemma": "ejercer",
        "upos": "VERB",
        "xpos": "vmip3p0",
        "feats": "Mood=Ind|Number=Plur|Person=3|Tense=Pres|VerbForm=Fin",
        "head": 77,
        "deprel": "csubj",
        "start_char": 996,
        "end_char": 1003
      },
      {
        "id": 74,
        "text": "una",
        "lemma": "uno",
        "upos": "DET",
        "xpos": "di0fs0",
        "feats": "Definite=Ind|Gender=Fem|Number=Sing|PronType=Art",
        "head": 75,
        "deprel": "det",
        "start_char": 1004,
        "end_char": 1007
      },
      {
        "id": 75,
        "text": "responsabilidad",
        "lemma": "responsabilidad",
        "upos": "NOUN",
        "xpos": "ncfs000",
        "feats": "Gender=Fem|Number=Sing",
        "head": 73,
        "deprel": "obj",
        "start_char": 1008,
        "end_char": 1023
      },
      {
        "id": 76,
        "text": "pública",
        "lemma": "público",
        "upos": "ADJ",
        "xpos": "aq0fs0",
        "feats": "Gender=Fem|Number=Sing",
        "head": 75,
        "deprel": "amod",
        "start_char": 1024,
        "end_char": 1031
      },
      {
        "id": 77,
        "text": "tienen",
        "lemma": "tener",
        "upos": "VERB",
        "xpos": "vmip3p0",
        "feats": "Mood=Ind|Number=Plur|Person=3|Tense=Pres|VerbForm=Fin",
        "head": 59,
        "deprel": "advcl",
        "start_char": 1032,
        "end_char": 1038
      },
      {
        "id": 78,
        "text": "una",
        "lemma": "uno",
        "upos": "DET",
        "xpos": "di0fs0",
        "feats": "Definite=Ind|Gender=Fem|Number=Sing|PronType=Art",
        "head": 80,
        "deprel": "det",
        "start_char": 1039,
        "end_char": 1042
      },
      {
        "id": 79,
        "text": "especial",
        "lemma": "especial",
        "upos": "ADJ",
        "xpos": "aq0cs0",
        "feats": "Number=Sing",
        "head": 80,
        "deprel": "amod",
        "start_char": 1043,
        "end_char": 1051
      },
      {
        "id": 80,
        "text": "obligación",
        "lemma": "obligación",
        "upos": "NOUN",
        "xpos": "ncfs000",
        "feats": "Gender=Fem|Number=Sing",
        "head": 77,
        "deprel": "obj",
        "start_char": 1052,
        "end_char": 1062
      },
      {
        "id": 81,
        "text": "de",
        "lemma": "de",
        "upos": "ADP",
        "xpos": "sps00",
        "feats": null,
        "head": 82,
        "deprel": "mark",
        "start_char": 1063,
        "end_char": 1065
      },
      {
        "id": 82,
        "text": "custodiar",
        "lemma": "custodiar",
        "upos": "VERB",
        "xpos": "vmn0000",
        "feats": "VerbForm=Inf",
        "head": 80,
        "deprel": "acl",
        "start_char": 1066,
        "end_char": 1075
      },
      {
        "id": 83,
        "text": "la",
        "lemma": "el",
        "upos": "DET",
        "xpos": "da0fs0",
        "feats": "Definite=Def|Gender=Fem|Number=Sing|PronType=Art",
        "head": 84,
        "deprel": "det",
        "start_char": 1076,
        "end_char": 1078
      },
      {
        "id": 84,
        "text": "palabra",
        "lemma": "palabra",
        "upos": "NOUN",
        "xpos": "ncfs000",
        "feats": "Gender=Fem|Number=Sing",
        "head": 82,
        "deprel": "obj",
        "start_char": 1079,
        "end_char": 1086
      },
      {
        "id": 85,
        "text": "para",
        "lemma": "para",
        "upos": "ADP",
        "xpos": "sps00",
        "feats": null,
        "head": 86,
        "deprel": "mark",
        "start_char": 1087,
        "end_char": 1091
      },
      {
        "id": 86,
        "text": "desarmar",
        "lemma": "desarmar",
        "upos": "VERB",
        "xpos": "vmn0000",
        "feats": "VerbForm=Inf",
        "head": 82,
        "deprel": "advcl",
        "start_char": 1092,
        "end_char": 1100
      },
      {
        "id": 87,
        "text": "el",
        "lemma": "el",
        "upos": "DET",
        "xpos": "da0ms0",
        "feats": "Definite=Def|Gender=Masc|Number=Sing|PronType=Art",
        "head": 88,
        "deprel": "det",
        "start_char": 1101,
        "end_char": 1103
      },
      {
        "id": 88,
        "text": "lenguaje",
        "lemma": "lenguaje",
        "upos": "NOUN",
        "xpos": "ncms000",
        "feats": "Gender=Masc|Number=Sing",
        "head": 86,
        "deprel": "obj",
        "start_char": 1104,
        "end_char": 1112
      },
      {
        "id": 89,
        "text": "”",
        "lemma": "\"",
        "upos": "PUNCT",
        "xpos": "fe",
        "feats": "PunctType=Quot",
        "head": 77,
        "deprel": "punct",
        "start_char": 1112,
        "end_char": 1113
      },
      {
        "id": 90,
        "text": ".",
        "lemma": ".",
        "upos": "PUNCT",
        "xpos": "fp",
        "feats": "PunctType=Peri",
        "head": 3,
        "deprel": "punct",
        "start_char": 1113,
        "end_char": 1114
      }
    ]
  },
  {
    "sent_id": 7,
    "text": "En su charla, Argúello ha recalcado que esa exigencia ética a los dirigentes políticos tiene que partir del buen ejemplo de los ciudadanos.",
    "tokens": [
      {
        "id": 1,
        "text": "En",
        "lemma": "en",
        "upos": "ADP",
        "xpos": "sps00",
        "feats": null,
        "head": 3,
        "deprel": "case",
        "start_char": 1115,
        "end_char": 1117
      },
      {
        "id": 2,
        "text": "su",
        "lemma": "su",
        "upos": "DET",
        "xpos": "dp3cs0",
        "feats": "Number=Sing|Person=3|Poss=Yes|PronType=Prs",
        "head": 3,
        "deprel": "det",
        "start_char": 1118,
        "end_char": 1120
      },
      {
        "id": 3,
        "text": "charla",
        "lemma": "charla",
        "upos": "NOUN",
        "xpos": "ncfs000",
        "feats": "Gender=Fem|Number=Sing",
        "head": 7,
        "deprel": "obl",
        "start_char": 1121,
        "end_char": 1127
      },
      {
        "id": 4,
        "text": ",",
        "lemma": ",",
        "upos": "PUNCT",
        "xpos": "fc",
        "feats": "PunctType=Comm",
        "head": 3,
        "deprel": "punct",
        "start_char": 1127,
        "end_char": 1128
      },
      {
        "id": 5,
        "text": "Argúello",
        "lemma": "Argúello",
        "upos": "PROPN",
        "xpos": "np00000",
        "feats": null,
        "head": 7,
        "deprel": "nsubj",
        "start_char": 1129,
        "end_char": 1137
      },
      {
        "id": 6,
        "text": "ha",
        "lemma": "haber",
        "upos": "AUX",
        "xpos": "vaip3s0",
        "feats": "Mood=Ind|Number=Sing|Person=3|Tense=Pres|VerbForm=Fin",
        "head": 7,
        "deprel": "aux",
        "start_char": 1138,
        "end_char": 1140
      },
      {
        "id": 7,
        "text": "recalcado",
        "lemma": "recalcar",
        "upos": "VERB",
        "xpos": "vmp00sm",
        "feats": "Gender=Masc|Number=Sing|Tense=Past|VerbForm=Part",
        "head": 0,
        "deprel": "root",
        "start_char": 1141,
        "end_char": 1150
      },
      {
        "id": 8,
        "text": "que",
        "lemma": "que",
        "upos": "SCONJ",
        "xpos": "cs",
        "feats": null,
        "head": 16,
        "deprel": "mark",
        "start_char": 1151,
        "end_char": 1154
      },
      {
        "id": 9,
        "text": "esa",
        "lemma": "ese",
        "upos": "DET",
        "xpos": "dd0fs0",
        "feats": "Gender=Fem|Number=Sing|PronType=Dem",
        "head": 10,
        "deprel": "det",
        "start_char": 1155,
        "end_char": 1158
      },
      {
        "id": 10,
        "text": "exigencia",
        "lemma": "exigencia",
        "upos": "NOUN",
        "xpos": "ncfs000",
        "feats": "Gender=Fem|Number=Sing",
        "head": 16,
        "deprel": "nsubj",
        "start_char": 1159,
        "end_char": 1168
      },
      {
        "id": 11,
        "text": "ética",
        "lemma": "ético",
        "upos": "ADJ",
        "xpos": "aq0fs0",
        "feats": "Gender=Fem|Number=Sing",
        "head": 10,
        "deprel": "amod",
        "start_char": 1169,
        "end_char": 1174
      },
      {
        "id": 12,
        "text": "a",
        "lemma": "a",
        "upos": "ADP",
        "xpos": "sps00",
        "feats": null,
        "head": 14,
        "deprel": "case",
        "start_char": 1175,
        "end_char": 1176
      },
      {
        "id": 13,
        "text": "los",
        "lemma": "el",
        "upos": "DET",
        "xpos": "da0mp0",
        "feats": "Definite=Def|Gender=Masc|Number=Plur|PronType=Art",
        "head": 14,
        "deprel": "det",
        "start_char": 1177,
        "end_char": 1180
      },
      {
        "id": 14,
        "text": "dirigentes",
        "lemma": "dirigente",
        "upos": "NOUN",
        "xpos": "nccp000",
        "feats": "Number=Plur",
        "head": 10,
        "deprel": "nmod",
        "start_char": 1181,
        "end_char": 1191
      },
      {
        "id": 15,
        "text": "políticos",
        "lemma": "político",
        "upos": "ADJ",
        "xpos": "aq0mp0",
        "feats": "Gender=Masc|Number=Plur",
        "head": 14,
        "deprel": "amod",
        "start_char": 1192,
        "end_char": 1201
      },
      {
        "id": 16,
        "text": "tiene",
        "lemma": "tener",
        "upos": "VERB",
        "xpos": "vmip3s0",
        "feats": "Mood=Ind|Number=Sing|Person=3|Tense=Pres|VerbForm=Fin",
        "head": 7,
        "deprel": "ccomp",
        "start_char": 1202,
        "end_char": 1207
      },
      {
        "id": 17,
        "text": "que",
        "lemma": "que",
        "upos": "SCONJ",
        "xpos": "cs",
        "feats": null,
        "head": 18,
        "deprel": "cc",
        "start_char": 1208,
        "end_char": 1211
      },
      {
        "id": 18,
        "text": "partir",
        "lemma": "partir",
        "upos": "NOUN",
        "xpos": null,
        "feats": null,
        "head": 16,
        "deprel": "conj",
        "start_char": 1212,
        "end_char": 1218
      },
      {
        "id": 19,
        "text": "de",
        "lemma": "de",
        "upos": "ADP",
        "xpos": "spcms",
        "feats": null,
        "head": 22,
        "deprel": "case",
        "start_char": null,
        "end_char": null
      },
      {
        "id": 20,
        "text": "el",
        "lemma": "el",
        "upos": "DET",
        "xpos": null,
        "feats": "Definite=Def|Gender=Masc|Number=Sing|PronType=Art",
        "head": 22,
        "deprel": "det",
        "start_char": null,
        "end_char": null
      },
      {
        "id": 21,
        "text": "buen",
        "lemma": "buen",
        "upos": "ADJ",
        "xpos": "aq0ms0",
        "feats": "Gender=Masc|Number=Sing",
        "head": 22,
        "deprel": "amod",
        "start_char": 1223,
        "end_char": 1227
      },
      {
        "id": 22,
        "text": "ejemplo",
        "lemma": "ejemplo",
        "upos": "NOUN",
        "xpos": "ncms000",
        "feats": "Gender=Masc|Number=Sing",
        "head": 16,
        "deprel": "conj",
        "start_char": 1228,
        "end_char": 1235
      },
      {
        "id": 23,
        "text": "de",
        "lemma": "de",
        "upos": "ADP",
        "xpos": "sps00",
        "feats": null,
        "head": 25,
        "deprel": "case",
        "start_char": 1236,
        "end_char": 1238
      },
      {
        "id": 24,
        "text": "los",
        "lemma": "el",
        "upos": "DET",
        "xpos": "da0mp0",
        "feats": "Definite=Def|Gender=Masc|Number=Plur|PronType=Art",
        "head": 25,
        "deprel": "det",
        "start_char": 1239,
        "end_char": 1242
      },
      {
        "id": 25,
        "text": "ciudadanos",
        "lemma": "ciudadano",
        "upos": "NOUN",
        "xpos": "ncmp000",
        "feats": "Gender=Masc|Number=Plur",
        "head": 22,
        "deprel": "nmod",
        "start_char": 1243,
        "end_char": 1253
      },
      {
        "id": 26,
        "text": ".",
        "lemma": ".",
        "upos": "PUNCT",
        "xpos": "fp",
        "feats": "PunctType=Peri",
        "head": 7,
        "deprel": "punct",
        "start_char": 1253,
        "end_char": 1254
      }
    ]
  },
  {
    "sent_id": 8,
    "text": "“Si hemos hecho trampas en el solitario a la hora de hacer la declaración de la renta, porque pensamos que ese es el pan de nuestros hijos, o si pedimos un contrato o mejor una factura en negro, ¡ojo!, porque las referencias éticas son para todos.",
    "tokens": [
      {
        "id": 1,
        "text": "“",
        "lemma": "\"",
        "upos": "PUNCT",
        "xpos": "fe",
        "feats": "PunctType=Quot",
        "head": 21,
        "deprel": "punct",
        "start_char": 1255,
        "end_char": 1256
      },
      {
        "id": 2,
        "text": "Si",
        "lemma": "si",
        "upos": "SCONJ",
        "xpos": "cs",
        "feats": null,
        "head": 4,
        "deprel": "mark",
        "start_char": 1256,
        "end_char": 1258
      },
      {
        "id": 3,
        "text": "hemos",
        "lemma": "haber",
        "upos": "AUX",
        "xpos": "vaip1p0",
        "feats": "Mood=Ind|Number=Plur|Person=1|Tense=Pres|VerbForm=Fin",
        "head": 4,
        "deprel": "aux",
        "start_char": 1259,
        "end_char": 1264
      },
      {
        "id": 4,
        "text": "hecho",
        "lemma": "hacer",
        "upos": "VERB",
        "xpos": "vmp00sm",
        "feats": "Gender=Masc|Number=Sing|Tense=Past|VerbForm=Part",
        "head": 53,
        "deprel": "advcl",
        "start_char": 1265,
        "end_char": 1270
      },
      {
        "id": 5,
        "text": "trampas",
        "lemma": "trampa",
        "upos": "NOUN",
        "xpos": "ncfp000",
        "feats": "Gender=Fem|Number=Plur",
        "head": 4,
        "deprel": "obj",
        "start_char": 1271,
        "end_char": 1278
      },
      {
        "id": 6,
        "text": "en",
        "lemma": "en",
        "upos": "ADP",
        "xpos": "sps00",
        "feats": null,
        "head": 8,
        "deprel": "case",
        "start_char": 1279,
        "end_char": 1281
      },
      {
        "id": 7,
        "text": "el",
        "lemma": "el",
        "upos": "DET",
        "xpos": "da0ms0",
        "feats": "Definite=Def|Gender=Masc|Number=Sing|PronType=Art",
        "head": 8,
        "deprel": "det",
        "start_char": 1282,
        "end_char": 1284
      },
      {
        "id": 8,
        "text": "solitario",
        "lemma": "solitario",
        "upos": "NOUN",
        "xpos": "ncms000",
        "feats": "Gender=Masc|Number=Sing",
        "head": 4,
        "deprel": "obl",
        "start_char": 1285,
        "end_char": 1294
      },
      {
        "id": 9,
        "text": "a",
        "lemma": "a",
        "upos": "ADP",
        "xpos": "sps00",
        "feats": null,
        "head": 11,
        "deprel": "case",
        "start_char": 1295,
        "end_char": 1296
      },
      {
        "id": 10,
        "text": "la",
        "lemma": "el",
        "upos": "DET",
        "xpos": "da0fs0",
        "feats": "Definite=Def|Gender=Fem|Number=Sing|PronType=Art",
        "head": 11,
        "deprel": "det",
        "start_char": 1297,
        "end_char": 1299
      },
      {
        "id": 11,
        "text": "hora",
        "lemma": "hora",
        "upos": "NOUN",
        "xpos": "ncfs000",
        "feats": "Gender=Fem|Number=Sing",
        "head": 4,
        "deprel": "obl",
        "start_char": 1300,
        "end_char": 1304
      },
      {
        "id": 12,
        "text": "de",
        "lemma": "de",
        "upos": "ADP",
        "xpos": "sps00",
        "feats": null,
        "head": 13,
        "deprel": "mark",
        "start_char": 1305,
        "end_char": 1307
      },
      {
        "id": 13,
        "text": "hacer",
        "lemma": "hacer",
        "upos": "VERB",
        "xpos": "vmn0000",
        "feats": "VerbForm=Inf",
        "head": 11,
        "deprel": "acl",
        "start_char": 1308,
        "end_char": 1313
      },
      {
        "id": 14,
        "text": "la",
        "lemma": "el",
        "upos": "DET",
        "xpos": "da0fs0",
        "feats": "Definite=Def|Gender=Fem|Number=Sing|PronType=Art",
        "head": 15,
        "deprel": "det",
        "start_char": 1314,
        "end_char": 1316
      },
      {
        "id": 15,
        "text": "declaración",
        "lemma": "declaración",
        "upos": "NOUN",
        "xpos": "ncfs000",
        "feats": "Gender=Fem|Number=Sing",
        "head": 13,
        "deprel": "obj",
        "start_char": 1317,
        "end_char": 1328
      },
      {
        "id": 16,
        "text": "de",
        "lemma": "de",
        "upos": "ADP",
        "xpos": "sps00",
        "feats": null,
        "head": 18,
        "deprel": "case",
        "start_char": 1329,
        "end_char": 1331
      },
      {
        "id": 17,
        "text": "la",
        "lemma": "el",
        "upos": "DET",
        "xpos": "da0fs0",
        "feats": "Definite=Def|Gender=Fem|Number=Sing|PronType=Art",
        "head": 18,
        "deprel": "det",
        "start_char": 1332,
        "end_char": 1334
      },
      {
        "id": 18,
        "text": "renta",
        "lemma": "renta",
        "upos": "NOUN",
        "xpos": "ncfs000",
        "feats": "Gender=Fem|Number=Sing",
        "head": 15,
        "deprel": "nmod",
        "start_char": 1335,
        "end_char": 1340
      },
      {
        "id": 19,
        "text": ",",
        "lemma": ",",
        "upos": "PUNCT",
        "xpos": "fc",
        "feats": "PunctType=Comm",
        "head": 4,
        "deprel": "punct",
        "start_char": 1340,
        "end_char": 1341
      },
      {
        "id": 20,
        "text": "porque",
        "lemma": "porque",
        "upos": "SCONJ",
        "xpos": "cs",
        "feats": null,
        "head": 21,
        "deprel": "mark",
        "start_char": 1342,
        "end_char": 1348
      },
      {
        "id": 21,
        "text": "pensamos",
        "lemma": "pensar",
        "upos": "VERB",
        "xpos": "vmip1p0",
        "feats": "Mood=Ind|Number=Plur|Person=1|Tense=Pres|VerbForm=Fin",
        "head": 4,
        "deprel": "advcl",
        "start_char": 1349,
        "end_char": 1357
      },
      {
        "id": 22,
        "text": "que",
        "lemma": "que",
        "upos": "SCONJ",
        "xpos": "cs",
        "feats": null,
        "head": 26,
        "deprel": "mark",
        "start_char": 1358,
        "end_char": 1361
      },
      {
        "id": 23,
        "text": "ese",
        "lemma": "ese",
        "upos": "PRON",
        "xpos": "pd0ms000",
        "feats": "Gender=Masc|Number=Sing|PronType=Dem",
        "head": 26,
        "deprel": "nsubj",
        "start_char": 1362,
        "end_char": 1365
      },
      {
        "id": 24,
        "text": "es",
        "lemma": "ser",
        "upos": "AUX",
        "xpos": "vsip3s0",
        "feats": "Mood=Ind|Number=Sing|Person=3|Tense=Pres|VerbForm=Fin",
        "head": 26,
        "deprel": "cop",
        "start_char": 1366,
        "end_char": 1368
      },
      {
        "id": 25,
        "text": "el",
        "lemma": "el",
        "upos": "DET",
        "xpos": "da0ms0",
        "feats": "Definite=Def|Gender=Masc|Number=Sing|PronType=Art",
        "head": 26,
        "deprel": "det",
        "start_char": 1369,
        "end_char": 1371
      },
      {
        "id": 26,
        "text": "pan",
        "lemma": "pan",
        "upos": "NOUN",
        "xpos": "ncms000",
        "feats": "Gender=Masc|Number=Sing",
        "head": 21,
        "deprel": "ccomp",
        "start_char": 1372,
        "end_char": 1375
      },
      {
        "id": 27,
        "text": "de",
        "lemma": "de",
        "upos": "ADP",
        "xpos": "sps00",
        "feats": null,
        "head": 29,
        "deprel": "case",
        "start_char": 1376,
        "end_char": 1378
      },
      {
        "id": 28,
        "text": "nuestros",
        "lemma": "nuestro",
        "upos": "DET",
        "xpos": "dp1mpp",
        "feats": "Gender=Masc|Number=Plur|Number[psor]=Plur|Person=1|Poss=Yes|PronType=Prs",
        "head": 29,
        "deprel": "det",
        "start_char": 1379,
        "end_char": 1387
      },
      {
        "id": 29,
        "text": "hijos",
        "lemma": "hijo",
        "upos": "NOUN",
        "xpos": "ncmp000",
        "feats": "Gender=Masc|Number=Plur",
        "head": 26,
        "deprel": "nmod",
        "start_char": 1388,
        "end_char": 1393
      },
      {
        "id": 30,
        "text": ",",
        "lemma": ",",
        "upos": "PUNCT",
        "xpos": "fc",
        "feats": "PunctType=Comm",
        "head": 33,
        "deprel": "punct",
        "start_char": 1393,
        "end_char": 1394
      },
      {
        "id": 31,
        "text": "o",
        "lemma": "o",
        "upos": "CCONJ",
        "xpos": "cc",
        "feats": null,
        "head": 33,
        "deprel": "cc",
        "start_char": 1395,
        "end_char": 1396
      },
      {
        "id": 32,
        "text": "si",
        "lemma": "si",
        "upos": "SCONJ",
        "xpos": "cs",
        "feats": null,
        "head": 33,
        "deprel": "mark",
        "start_char": 1397,
        "end_char": 1399
      },
      {
        "id": 33,
        "text": "pedimos",
        "lemma": "pedir",
        "upos": "VERB",
        "xpos": "vmip1p0",
        "feats": "Mood=Ind|Number=Plur|Person=1|Tense=Pres|VerbForm=Fin",
        "head": 26,
        "deprel": "conj",
        "start_char": 1400,
        "end_char": 1407
      },
      {
        "id": 34,
        "text": "un",
        "lemma": "uno",
        "upos": "DET",
        "xpos": "di0ms0",
        "feats": "Definite=Ind|Gender=Masc|Number=Sing|PronType=Art",
        "head": 35,
        "deprel": "det",
        "start_char": 1408,
        "end_char": 1410
      },
      {
        "id": 35,
        "text": "contrato",
        "lemma": "contrato",
        "upos": "NOUN",
        "xpos": "ncms000",
        "feats": "Gender=Masc|Number=Sing",
        "head": 33,
        "deprel": "obj",
        "start_char": 1411,
        "end_char": 1419
      },
      {
        "id": 36,
        "text": "o",
        "lemma": "o",
        "upos": "CCONJ",
        "xpos": "cc",
        "feats": null,
        "head": 37,
        "deprel": "cc",
        "start_char": 1420,
        "end_char": 1421
      },
      {
        "id": 37,
        "text": "mejor",
        "lemma": "mejor",
        "upos": "ADJ",
        "xpos": "aq0cs0",
        "feats": "Degree=Cmp|Number=Sing",
        "head": 35,
        "deprel": "conj",
        "start_char": 1422,
        "end_char": 1427
      },
      {
        "id": 38,
        "text": "una",
        "lemma": "uno",
        "upos": "DET",
        "xpos": "di0fs0",
        "feats": "Definite=Ind|Gender=Fem|Number=Sing|PronType=Art",
        "head": 39,
        "deprel": "det",
        "start_char": 1428,
        "end_char": 1431
      },
      {
        "id": 39,
        "text": "factura",
        "lemma": "factura",
        "upos": "NOUN",
        "xpos": "ncfs000",
        "feats": "Gender=Fem|Number=Sing",
        "head": 33,
        "deprel": "obj",
        "start_char": 1432,
        "end_char": 1439
      },
      {
        "id": 40,
        "text": "en",
        "lemma": "en",
        "upos": "ADP",
        "xpos": "rg00",
        "feats": null,
        "head": 41,
        "deprel": "case",
        "start_char": 1440,
        "end_char": 1442
      },
      {
        "id": 41,
        "text": "negro",
        "lemma": "negro",
        "upos": "NOUN",
        "xpos": "ncms000",
        "feats": "Gender=Masc",
        "head": 39,
        "deprel": "nmod",
        "start_char": 1443,
        "end_char": 1448
      },
      {
        "id": 42,
        "text": ",",
        "lemma": ",",
        "upos": "PUNCT",
        "xpos": "fc",
        "feats": "PunctType=Comm",
        "head": 44,
        "deprel": "punct",
        "start_char": 1448,
        "end_char": 1449
      },
      {
        "id": 43,
        "text": "¡",
        "lemma": "¡",
        "upos": "PUNCT",
        "xpos": "faa",
        "feats": "PunctSide=Ini|PunctType=Excl",
        "head": 44,
        "deprel": "punct",
        "start_char": 1450,
        "end_char": 1451
      },
      {
        "id": 44,
        "text": "ojo",
        "lemma": "ojo",
        "upos": "NOUN",
        "xpos": "ncms000",
        "feats": "Gender=Masc|Number=Sing",
        "head": 39,
        "deprel": "appos",
        "start_char": 1451,
        "end_char": 1454
      },
      {
        "id": 45,
        "text": "!",
        "lemma": "!",
        "upos": "PUNCT",
        "xpos": "fat",
        "feats": "PunctSide=Fin|PunctType=Excl",
        "head": 44,
        "deprel": "punct",
        "start_char": 1454,
        "end_char": 1455
      },
      {
        "id": 46,
        "text": ",",
        "lemma": ",",
        "upos": "PUNCT",
        "xpos": "fc",
        "feats": "PunctType=Comm",
        "head": 53,
        "deprel": "punct",
        "start_char": 1455,
        "end_char": 1456
      },
      {
        "id": 47,
        "text": "porque",
        "lemma": "porque",
        "upos": "SCONJ",
        "xpos": "cs",
        "feats": null,
        "head": 53,
        "deprel": "mark",
        "start_char": 1457,
        "end_char": 1463
      },
      {
        "id": 48,
        "text": "las",
        "lemma": "el",
        "upos": "DET",
        "xpos": "da0fp0",
        "feats": "Definite=Def|Gender=Fem|Number=Plur|PronType=Art",
        "head": 49,
        "deprel": "det",
        "start_char": 1464,
        "end_char": 1467
      },
      {
        "id": 49,
        "text": "referencias",
        "lemma": "referencia",
        "upos": "NOUN",
        "xpos": "ncfp000",
        "feats": "Gender=Fem|Number=Plur",
        "head": 53,
        "deprel": "nsubj",
        "start_char": 1468,
        "end_char": 1479
      },
      {
        "id": 50,
        "text": "éticas",
        "lemma": "ético",
        "upos": "ADJ",
        "xpos": "aq0fp0",
        "feats": "Gender=Fem|Number=Plur",
        "head": 49,
        "deprel": "amod",
        "start_char": 1480,
        "end_char": 1486
      },
      {
        "id": 51,
        "text": "son",
        "lemma": "ser",
        "upos": "AUX",
        "xpos": "vsip3p0",
        "feats": "Mood=Ind|Number=Plur|Person=3|Tense=Pres|VerbForm=Fin",
        "head": 53,
        "deprel": "cop",
        "start_char": 1487,
        "end_char": 1490
      },
      {
        "id": 52,
        "text": "para",
        "lemma": "para",
        "upos": "ADP",
        "xpos": "sps00",
        "feats": null,
        "head": 53,
        "deprel": "case",
        "start_char": 1491,
        "end_char": 1495
      },
      {
        "id": 53,
        "text": "todos",
        "lemma": "todo",
        "upos": "PRON",
        "xpos": "pi0mp000",
        "feats": "Gender=Masc|Number=Plur|PronType=Tot",
        "head": 0,
        "deprel": "root",
        "start_char": 1496,
        "end_char": 1501
      },
      {
        "id": 54,
        "text": ".",
        "lemma": ".",
        "upos": "PUNCT",
        "xpos": "fp",
        "feats": "PunctType=Peri",
        "head": 4,
        "deprel": "punct",
        "start_char": 1501,
        "end_char": 1502
      }
    ]
  },
  {
    "sent_id": 9,
    "text": "Porque si no hay un pueblo, un demos, con referencia ética, ¿cómo vas a exigirlo a alguien que sea tu representante?”, se ha preguntado en la clausura de la Escuela de Verano organizada por la Conferencia Episcopal Española, la Universidad Pontificia de Salamanca y la Fundación Pablo VI.",
    "tokens": [
      {
        "id": 1,
        "text": "Porque",
        "lemma": "porque",
        "upos": "SCONJ",
        "xpos": "cs",
        "feats": null,
        "head": 17,
        "deprel": "mark",
        "start_char": 1503,
        "end_char": 1509
      },
      {
        "id": 2,
        "text": "si",
        "lemma": "si",
        "upos": "SCONJ",
        "xpos": "cs",
        "feats": null,
        "head": 4,
        "deprel": "mark",
        "start_char": 1510,
        "end_char": 1512
      },
      {
        "id": 3,
        "text": "no",
        "lemma": "no",
        "upos": "ADV",
        "xpos": "rn",
        "feats": "Polarity=Neg",
        "head": 4,
        "deprel": "advmod",
        "start_char": 1513,
        "end_char": 1515
      },
      {
        "id": 4,
        "text": "hay",
        "lemma": "haber",
        "upos": "VERB",
        "xpos": "vaip3s0",
        "feats": "Mood=Ind|Number=Sing|Person=3|Tense=Pres|VerbForm=Fin",
        "head": 32,
        "deprel": "advcl",
        "start_char": 1516,
        "end_char": 1519
      },
      {
        "id": 5,
        "text": "un",
        "lemma": "uno",
        "upos": "DET",
        "xpos": "di0ms0",
        "feats": "Definite=Ind|Gender=Masc|Number=Sing|PronType=Art",
        "head": 6,
        "deprel": "det",
        "start_char": 1520,
        "end_char": 1522
      },
      {
        "id": 6,
        "text": "pueblo",
        "lemma": "pueblo",
        "upos": "NOUN",
        "xpos": "ncms000",
        "feats": "Gender=Masc|Number=Sing",
        "head": 4,
        "deprel": "obj",
        "start_char": 1523,
        "end_char": 1529
      },
      {
        "id": 7,
        "text": ",",
        "lemma": ",",
        "upos": "PUNCT",
        "xpos": "fc",
        "feats": "PunctType=Comm",
        "head": 9,
        "deprel": "punct",
        "start_char": 1529,
        "end_char": 1530
      },
      {
        "id": 8,
        "text": "un",
        "lemma": "uno",
        "upos": "DET",
        "xpos": "di0ms0",
        "feats": "Definite=Ind|Gender=Masc|Number=Sing|PronType=Art",
        "head": 9,
        "deprel": "det",
        "start_char": 1531,
        "end_char": 1533
      },
      {
        "id": 9,
        "text": "demos",
        "lemma": "demos",
        "upos": "NOUN",
        "xpos": "ncmp000",
        "feats": "Gender=Masc|Number=Plur",
        "head": 17,
        "deprel": "nsubj",
        "start_char": 1534,
        "end_char": 1539
      },
      {
        "id": 10,
        "text": ",",
        "lemma": ",",
        "upos": "PUNCT",
        "xpos": "fc",
        "feats": "PunctType=Comm",
        "head": 12,
        "deprel": "punct",
        "start_char": 1539,
        "end_char": 1540
      },
      {
        "id": 11,
        "text": "con",
        "lemma": "con",
        "upos": "ADP",
        "xpos": "sps00",
        "feats": null,
        "head": 12,
        "deprel": "case",
        "start_char": 1541,
        "end_char": 1544
      },
      {
        "id": 12,
        "text": "referencia",
        "lemma": "referencia",
        "upos": "NOUN",
        "xpos": "ncfs000",
        "feats": "Gender=Fem|Number=Sing",
        "head": 9,
        "deprel": "nmod",
        "start_char": 1545,
        "end_char": 1555
      },
      {
        "id": 13,
        "text": "ética",
        "lemma": "ético",
        "upos": "ADJ",
        "xpos": "aq0fs0",
        "feats": "Gender=Fem|Number=Sing",
        "head": 12,
        "deprel": "amod",
        "start_char": 1556,
        "end_char": 1561
      },
      {
        "id": 14,
        "text": ",",
        "lemma": ",",
        "upos": "PUNCT",
        "xpos": "fc",
        "feats": "PunctType=Comm",
        "head": 12,
        "deprel": "punct",
        "start_char": 1561,
        "end_char": 1562
      },
      {
        "id": 15,
        "text": "¿",
        "lemma": "¿",
        "upos": "PUNCT",
        "xpos": "fia",
        "feats": "PunctSide=Ini|PunctType=Qest",
        "head": 17,
        "deprel": "punct",
        "start_char": 1563,
        "end_char": 1564
      },
      {
        "id": 16,
        "text": "cómo",
        "lemma": "cómo",
        "upos": "PRON",
        "xpos": "pt000000",
        "feats": "PronType=Ind",
        "head": 17,
        "deprel": "obl",
        "start_char": 1564,
        "end_char": 1568
      },
      {
        "id": 17,
        "text": "vas",
        "lemma": "ir",
        "upos": "VERB",
        "xpos": "vmip2s0",
        "feats": "Mood=Ind|Number=Sing|Person=1|Tense=Pres|VerbForm=Fin",
        "head": 32,
        "deprel": "xcomp",
        "start_char": 1569,
        "end_char": 1572
      },
      {
        "id": 18,
        "text": "a",
        "lemma": "a",
        "upos": "ADP",
        "xpos": "sps00",
        "feats": null,
        "head": 19,
        "deprel": "mark",
        "start_char": 1573,
        "end_char": 1574
      },
      {
        "id": 19,
        "text": "exigir",
        "lemma": "exigir",
        "upos": "VERB",
        "xpos": "vmn0000",
        "feats": "VerbForm=Inf",
        "head": 17,
        "deprel": "xcomp",
        "start_char": 1575,
        "end_char": 1581
      },
      {
        "id": 20,
        "text": "lo",
        "lemma": "él",
        "upos": "PRON",
        "xpos": null,
        "feats": "Case=Acc|Gender=Masc|Number=Sing|Person=3|PrepCase=Npr|PronType=Prs",
        "head": 19,
        "deprel": "obj",
        "start_char": 1581,
        "end_char": 1583
      },
      {
        "id": 21,
        "text": "a",
        "lemma": "a",
        "upos": "ADP",
        "xpos": "sps00",
        "feats": null,
        "head": 22,
        "deprel": "case",
        "start_char": 1584,
        "end_char": 1585
      },
      {
        "id": 22,
        "text": "alguien",
        "lemma": "alguien",
        "upos": "PRON",
        "xpos": "pi0cs000",
        "feats": "Number=Sing|PronType=Ind",
        "head": 19,
        "deprel": "obl:arg",
        "start_char": 1586,
        "end_char": 1593
      },
      {
        "id": 23,
        "text": "que",
        "lemma": "que",
        "upos": "PRON",
        "xpos": "pr0cn000",
        "feats": "PronType=Rel",
        "head": 26,
        "deprel": "nsubj",
        "start_char": 1594,
        "end_char": 1597
      },
      {
        "id": 24,
        "text": "sea",
        "lemma": "ser",
        "upos": "AUX",
        "xpos": "vssp3s0",
        "feats": "Mood=Sub|Number=Sing|Person=3|Tense=Pres|VerbForm=Fin",
        "head": 26,
        "deprel": "cop",
        "start_char": 1598,
        "end_char": 1601
      },
      {
        "id": 25,
        "text": "tu",
        "lemma": "tu",
        "upos": "DET",
        "xpos": "dp2css",
        "feats": "Number=Sing|Number[psor]=Sing|Person=2|Poss=Yes|PronType=Prs",
        "head": 26,
        "deprel": "det",
        "start_char": 1602,
        "end_char": 1604
      },
      {
        "id": 26,
        "text": "representante",
        "lemma": "representante",
        "upos": "NOUN",
        "xpos": "nccs000",
        "feats": "Number=Sing",
        "head": 22,
        "deprel": "acl",
        "start_char": 1605,
        "end_char": 1618
      },
      {
        "id": 27,
        "text": "?",
        "lemma": "?",
        "upos": "PUNCT",
        "xpos": "fit",
        "feats": "PunctSide=Fin|PunctType=Qest",
        "head": 17,
        "deprel": "punct",
        "start_char": 1618,
        "end_char": 1619
      },
      {
        "id": 28,
        "text": "”",
        "lemma": "\"",
        "upos": "PUNCT",
        "xpos": "fe",
        "feats": "PunctType=Quot",
        "head": 17,
        "deprel": "punct",
        "start_char": 1619,
        "end_char": 1620
      },
      {
        "id": 29,
        "text": ",",
        "lemma": ",",
        "upos": "PUNCT",
        "xpos": "fc",
        "feats": "PunctType=Comm",
        "head": 17,
        "deprel": "punct",
        "start_char": 1620,
        "end_char": 1621
      },
      {
        "id": 30,
        "text": "se",
        "lemma": "él",
        "upos": "PRON",
        "xpos": "p0300000",
        "feats": "Case=Acc|Person=3|PrepCase=Npr|PronType=Prs|Reflex=Yes",
        "head": 32,
        "deprel": "expl:pv",
        "start_char": 1622,
        "end_char": 1624
      },
      {
        "id": 31,
        "text": "ha",
        "lemma": "haber",
        "upos": "AUX",
        "xpos": "vaip3s0",
        "feats": "Mood=Ind|Number=Sing|Person=3|Tense=Pres|VerbForm=Fin",
        "head": 32,
        "deprel": "aux",
        "start_char": 1625,
        "end_char": 1627
      },
      {
        "id": 32,
        "text": "preguntado",
        "lemma": "preguntar",
        "upos": "VERB",
        "xpos": "vmp00sm",
        "feats": "Gender=Masc|Number=Sing|Tense=Past|VerbForm=Part",
        "head": 0,
        "deprel": "root",
        "start_char": 1628,
        "end_char": 1638
      },
      {
        "id": 33,
        "text": "en",
        "lemma": "en",
        "upos": "ADP",
        "xpos": "sps00",
        "feats": null,
        "head": 35,
        "deprel": "case",
        "start_char": 1639,
        "end_char": 1641
      },
      {
        "id": 34,
        "text": "la",
        "lemma": "el",
        "upos": "DET",
        "xpos": "da0fs0",
        "feats": "Definite=Def|Gender=Fem|Number=Sing|PronType=Art",
        "head": 35,
        "deprel": "det",
        "start_char": 1642,
        "end_char": 1644
      },
      {
        "id": 35,
        "text": "clausura",
        "lemma": "clausura",
        "upos": "NOUN",
        "xpos": "ncfs000",
        "feats": "Gender=Fem|Number=Sing",
        "head": 32,
        "deprel": "obl",
        "start_char": 1645,
        "end_char": 1653
      },
      {
        "id": 36,
        "text": "de",
        "lemma": "de",
        "upos": "ADP",
        "xpos": "sps00",
        "feats": null,
        "head": 38,
        "deprel": "case",
        "start_char": 1654,
        "end_char": 1656
      },
      {
        "id": 37,
        "text": "la",
        "lemma": "el",
        "upos": "DET",
        "xpos": "da0fs0",
        "feats": "Definite=Def|Gender=Fem|Number=Sing|PronType=Art",
        "head": 38,
        "deprel": "det",
        "start_char": 1657,
        "end_char": 1659
      },
      {
        "id": 38,
        "text": "Escuela",
        "lemma": "Escuela",
        "upos": "PROPN",
        "xpos": "np00000",
        "feats": null,
        "head": 35,
        "deprel": "nmod",
        "start_char": 1660,
        "end_char": 1667
      },
      {
        "id": 39,
        "text": "de",
        "lemma": "de",
        "upos": "ADP",
        "xpos": null,
        "feats": null,
        "head": 40,
        "deprel": "case",
        "start_char": 1668,
        "end_char": 1670
      },
      {
        "id": 40,
        "text": "Verano",
        "lemma": "Verano",
        "upos": "PROPN",
        "xpos": null,
        "feats": null,
        "head": 38,
        "deprel": "flat",
        "start_char": 1671,
        "end_char": 1677
      },
      {
        "id": 41,
        "text": "organizada",
        "lemma": "organizado",
        "upos": "ADJ",
        "xpos": "aq0fsp",
        "feats": "Gender=Fem|Number=Sing|VerbForm=Part",
        "head": 38,
        "deprel": "amod",
        "start_char": 1678,
        "end_char": 1688
      },
      {
        "id": 42,
        "text": "por",
        "lemma": "por",
        "upos": "ADP",
        "xpos": "sps00",
        "feats": null,
        "head": 44,
        "deprel": "case",
        "start_char": 1689,
        "end_char": 1692
      },
      {
        "id": 43,
        "text": "la",
        "lemma": "el",
        "upos": "DET",
        "xpos": "da0fs0",
        "feats": "Definite=Def|Gender=Fem|Number=Sing|PronType=Art",
        "head": 44,
        "deprel": "det",
        "start_char": 1693,
        "end_char": 1695
      },
      {
        "id": 44,
        "text": "Conferencia",
        "lemma": "Conferencia",
        "upos": "PROPN",
        "xpos": "np00000",
        "feats": null,
        "head": 41,
        "deprel": "obl:agent",
        "start_char": 1696,
        "end_char": 1707
      },
      {
        "id": 45,
        "text": "Episcopal",
        "lemma": "Episcopal",
        "upos": "PROPN",
        "xpos": null,
        "feats": null,
        "head": 44,
        "deprel": "flat",
        "start_char": 1708,
        "end_char": 1717
      },
      {
        "id": 46,
        "text": "Española",
        "lemma": "Española",
        "upos": "PROPN",
        "xpos": null,
        "feats": null,
        "head": 44,
        "deprel": "flat",
        "start_char": 1718,
        "end_char": 1726
      },
      {
        "id": 47,
        "text": ",",
        "lemma": ",",
        "upos": "PUNCT",
        "xpos": "fc",
        "feats": "PunctType=Comm",
        "head": 49,
        "deprel": "punct",
        "start_char": 1726,
        "end_char": 1727
      },
      {
        "id": 48,
        "text": "la",
        "lemma": "el",
        "upos": "DET",
        "xpos": "da0fs0",
        "feats": "Definite=Def|Gender=Fem|Number=Sing|PronType=Art",
        "head": 49,
        "deprel": "det",
        "start_char": 1728,
        "end_char": 1730
      },
      {
        "id": 49,
        "text": "Universidad",
        "lemma": "universidad",
        "upos": "PROPN",
        "xpos": "np00000",
        "feats": null,
        "head": 44,
        "deprel": "flat",
        "start_char": 1731,
        "end_char": 1742
      },
      {
        "id": 50,
        "text": "Pontificia",
        "lemma": "pontificio",
        "upos": "PROPN",
        "xpos": null,
        "feats": null,
        "head": 49,
        "deprel": "flat",
        "start_char": 1743,
        "end_char": 1753
      },
      {
        "id": 51,
        "text": "de",
        "lemma": "de",
        "upos": "ADP",
        "xpos": null,
        "feats": null,
        "head": 52,
        "deprel": "case",
        "start_char": 1754,
        "end_char": 1756
      },
      {
        "id": 52,
        "text": "Salamanca",
        "lemma": "Salamanca",
        "upos": "PROPN",
        "xpos": null,
        "feats": null,
        "head": 49,
        "deprel": "flat",
        "start_char": 1757,
        "end_char": 1766
      },
      {
        "id": 53,
        "text": "y",
        "lemma": "y",
        "upos": "CCONJ",
        "xpos": "cc",
        "feats": null,
        "head": 55,
        "deprel": "cc",
        "start_char": 1767,
        "end_char": 1768
      },
      {
        "id": 54,
        "text": "la",
        "lemma": "el",
        "upos": "DET",
        "xpos": "da0fs0",
        "feats": "Definite=Def|Gender=Fem|Number=Sing|PronType=Art",
        "head": 55,
        "deprel": "det",
        "start_char": 1769,
        "end_char": 1771
      },
      {
        "id": 55,
        "text": "Fundación",
        "lemma": "Fundación",
        "upos": "PROPN",
        "xpos": "np00000",
        "feats": null,
        "head": 44,
        "deprel": "conj",
        "start_char": 1772,
        "end_char": 1781
      },
      {
        "id": 56,
        "text": "Pablo",
        "lemma": "Pablo",
        "upos": "PROPN",
        "xpos": null,
        "feats": null,
        "head": 55,
        "deprel": "flat",
        "start_char": 1782,
        "end_char": 1787
      },
      {
        "id": 57,
        "text": "VI",
        "lemma": "vi",
        "upos": "NUM",
        "xpos": null,
        "feats": "NumForm=Roman|NumType=Card",
        "head": 55,
        "deprel": "nummod",
        "start_char": 1788,
        "end_char": 1790
      },
      {
        "id": 58,
        "text": ".",
        "lemma": ".",
        "upos": "PUNCT",
        "xpos": "fp",
        "feats": "PunctType=Peri",
        "head": 32,
        "deprel": "punct",
        "start_char": 1790,
        "end_char": 1791
      }
    ]
  }
]